gaia_oc_amd/__init__.py
gaia_oc_amd/build_sets.py
gaia_oc_amd/create_gaia_credentials_file.py
gaia_oc_amd/download_startup_data.py
gaia_oc_amd/evaluate_clusters.py
gaia_oc_amd/io.py
gaia_oc_amd/train_deep_sets_model.py
gaia_oc_amd/utils.py
gaia_oc_amd/candidate_evaluation/__init__.py
gaia_oc_amd/candidate_evaluation/diagnostics.py
gaia_oc_amd/candidate_evaluation/membership_probability.py
gaia_oc_amd/candidate_evaluation/visualization.py
gaia_oc_amd/candidate_evaluation/pretrained_model/hyper_parameters
gaia_oc_amd/candidate_evaluation/pretrained_model/model_parameters
gaia_oc_amd/candidate_evaluation/pretrained_models/DS10_v01/hyper_parameters
gaia_oc_amd/candidate_evaluation/pretrained_models/DS10_v01/model_parameters
gaia_oc_amd/candidate_evaluation/pretrained_models/DS10_v02/hyper_parameters
gaia_oc_amd/candidate_evaluation/pretrained_models/DS10_v02/model_parameters
gaia_oc_amd/data_preparation/LogErrVsMagSpline.csv
gaia_oc_amd/data_preparation/__init__.py
gaia_oc_amd/data_preparation/candidate_selection.py
gaia_oc_amd/data_preparation/cluster.py
gaia_oc_amd/data_preparation/cone_preprocessing.py
gaia_oc_amd/data_preparation/datasets.py
gaia_oc_amd/data_preparation/features.py
gaia_oc_amd/data_preparation/isochrone_preprocessing.py
gaia_oc_amd/data_preparation/query.py
gaia_oc_amd/data_preparation/source_sets.py
gaia_oc_amd/machine_learning/__init__.py
gaia_oc_amd/machine_learning/deepsets_zaheer.py
gaia_oc_amd/machine_learning/training.py
gaia_oc_amd-0.2.1.dist-info/LICENSE
gaia_oc_amd-0.2.1.dist-info/METADATA
gaia_oc_amd-0.2.1.dist-info/WHEEL
gaia_oc_amd-0.2.1.dist-info/top_level.txt
gaia_oc_amd-0.2.1.dist-info/RECORD
