Metadata-Version: 2.1
Name: gaia-oc-amd
Version: 0.2.1
Summary: Machine learning tool for the determination of new members of open clusters using Gaia data.
Home-page: https://github.com/MGJvanGroeningen/gaia_oc_amd
Author: Matthijs G. J. van Groeningen
Author-email: matthijsvangroeningen@gmail.com
License: UNKNOWN
Platform: UNKNOWN
Classifier: Programming Language :: Python :: 3
Classifier: License :: OSI Approved :: MIT License
Classifier: Operating System :: OS Independent
Requires-Python: >=3.6
Requires-Dist: numpy
Requires-Dist: pandas
Requires-Dist: matplotlib
Requires-Dist: matplotlib-venn
Requires-Dist: torch
Requires-Dist: torchvision
Requires-Dist: scipy
Requires-Dist: tqdm
Requires-Dist: astropy
Requires-Dist: astroquery
Requires-Dist: requests
Requires-Dist: lxml
Requires-Dist: gaiadr3-zeropoint
Requires-Dist: dustapprox
Requires-Dist: scikit-learn
